personmatchmodule/__init__.py
personmatchmodule/py.typed
personmatchmodule/logics/__init__.py
personmatchmodule/logics/rules_generator.py
personmatchmodule/logics/score_calculator.py
personmatchmodule/models/__init__.py
personmatchmodule/models/constants.py
personmatchmodule/models/rule.py
tests/__init__.py
tests/test_person_one_to_one_match.py
person_match_module-0.1.5.dist-info/LICENSE
person_match_module-0.1.5.dist-info/METADATA
person_match_module-0.1.5.dist-info/WHEEL
person_match_module-0.1.5.dist-info/top_level.txt
person_match_module-0.1.5.dist-info/RECORD
